trajpy_ui/__init__.py
trajpy_ui/ui.py
trajpy_ui/utils.py
trajpy_ui/assets/logo.png
trajpy_ui-0.2.0.dist-info/METADATA
trajpy_ui-0.2.0.dist-info/WHEEL
trajpy_ui-0.2.0.dist-info/licenses/LICENSE
trajpy_ui-0.2.0.dist-info/RECORD
