Metadata-Version: 2.4
Name: trajpy-ui
Version: 0.2.0
Summary: Trajpy UI - empowering feature engineering for trajectory analysis across domains.
Project-URL: homepage, https://github.com/ocbe-uio/trajpy-ui
Author-email: Maurício Moreira Soares <trajpy@protonmail.ch>
License-Expression: GPL-3.0
License-File: LICENSE
Keywords: python,repeated-mesurements,time-series,trajectory
Requires-Python: <4.0,>=3.11
Requires-Dist: matplotlib>=3.10.8
Requires-Dist: nicegui>=3.6.1
Requires-Dist: trajpy>=1.4.3
